{
	"configurations" : 
	[
		{
			"directories" : 
			[
				{
					"build" : ".",
					"childIndexes" : 
					[
						1
					],
					"jsonFile" : "directory-.-Debug-f5ebdc15457944623624.json",
					"minimumCMakeVersion" : 
					{
						"string" : "3.20"
					},
					"projectIndex" : 0,
					"source" : ".",
					"targetIndexes" : 
					[
						0
					]
				},
				{
					"build" : "3rdpart",
					"childIndexes" : 
					[
						2
					],
					"jsonFile" : "directory-3rdpart-Debug-8155d260bb18c8cb5d6b.json",
					"minimumCMakeVersion" : 
					{
						"string" : "3.20"
					},
					"parentIndex" : 0,
					"projectIndex" : 0,
					"source" : "3rdpart"
				},
				{
					"build" : "3rdpart/glm",
					"jsonFile" : "directory-3rdpart.glm-Debug-348703705f4671fa37ba.json",
					"minimumCMakeVersion" : 
					{
						"string" : "3.20"
					},
					"parentIndex" : 1,
					"projectIndex" : 0,
					"source" : "3rdpart/glm"
				}
			],
			"name" : "Debug",
			"projects" : 
			[
				{
					"directoryIndexes" : 
					[
						0,
						1,
						2
					],
					"name" : "main",
					"targetIndexes" : 
					[
						0
					]
				}
			],
			"targets" : 
			[
				{
					"directoryIndex" : 0,
					"id" : "main::@6890427a1f51a3e7e1df",
					"jsonFile" : "target-main-Debug-6cee6287889fc6a7cd41.json",
					"name" : "main",
					"projectIndex" : 0
				}
			]
		}
	],
	"kind" : "codemodel",
	"paths" : 
	{
		"build" : "/home/admin/\u6587\u6863/OpenGL/RayTracing/build",
		"source" : "/home/admin/\u6587\u6863/OpenGL/RayTracing"
	},
	"version" : 
	{
		"major" : 2,
		"minor" : 7
	}
}
